sshdol/__init__.py
sshdol/base.py
sshdol/tests/__init__.py
sshdol/tests/test_base.py
sshdol/tests/utils_for_testing.py
sshdol-0.0.8.dist-info/LICENSE
sshdol-0.0.8.dist-info/METADATA
sshdol-0.0.8.dist-info/WHEEL
sshdol-0.0.8.dist-info/top_level.txt
sshdol-0.0.8.dist-info/RECORD
