Metadata-Version: 2.1
Name: sshdol
Version: 0.0.8
Summary: Easy dict-like access to server files
Home-page: https://github.com/i2mint/sshdol
License: apache-2.0
Platform: any
License-File: LICENSE
Requires-Dist: py2store
Requires-Dist: paramiko
